spectralLib/__init__.py
spectralLib/error.py
spectralLib/metadata.py
spectralLib/CIE/__init__.py
spectralLib/CIE/illuminant.py
spectralLib/CIE/observer.py
spectralLib/CIE/spectral2rgb.py
spectralLib/cube/__init__.py
spectralLib/cube/generatetextures.py
spectralLib/display/__init__.py
spectralLib/display/colorimage.py
spectralLib/display/spectralcube.py
spectralLib/display/spectralimage.py
spectralLib/display/spectralsignature.py
spectralLib/load/__init__.py
spectralLib/load/file.py
spectralLib/load/mat.py
spectralLib-0.0.3.dist-info/LICENSE
spectralLib-0.0.3.dist-info/METADATA
spectralLib-0.0.3.dist-info/WHEEL
spectralLib-0.0.3.dist-info/top_level.txt
spectralLib-0.0.3.dist-info/RECORD
