Metadata-Version: 2.1
Name: spectralLib
Version: 0.0.3
Summary: A python library for analyzing multi and hyper spectral images.
Home-page: https://gitlab.com/TomAmpiath/spectralLib
Author: Tom George Ampiath
Author-email: itomgeorgeampiath@gmail.com
License: UNKNOWN
Keywords: spectralUI hyperspectral multispectral PySide2 Qt spectralLib
Platform: UNKNOWN
Classifier: Development Status :: 4 - Beta
Classifier: Intended Audience :: Science/Research
Classifier: Natural Language :: English
Classifier: Topic :: Scientific/Engineering
Classifier: Programming Language :: Python :: 3
Classifier: License :: OSI Approved :: GNU General Public License v3 or later (GPLv3+)
Classifier: Operating System :: OS Independent
Requires-Python: >=3.6
Requires-Dist: numpy
Requires-Dist: matplotlib
Requires-Dist: scipy
Requires-Dist: vtk
